Library_sink_package/BookClass.py
Library_sink_package/Library.py
Library_sink_package/Library_run.py
Library_sink_package/ReaderClass.py
Library_sink_package/__init__.py
Library_sink_package-1.0.2.dist-info/METADATA
Library_sink_package-1.0.2.dist-info/WHEEL
Library_sink_package-1.0.2.dist-info/top_level.txt
Library_sink_package-1.0.2.dist-info/RECORD
