Metadata-Version: 2.1
Name: Library-sink-package
Version: 1.0.2
Summary: Library of books
Home-page: UNKNOWN
Author: Sergiy Sinkevich
Author-email: sinkevich2492@i.ua
License: UNKNOWN
Platform: UNKNOWN
